{
  "api": "1",
  "auth": "github:Raku",
  "authors": [
    "Joel D. S. <@noisegul>",
    "Tim Siegel <github:softmoth>"
  ],
  "build-depends": [
  ],
  "depends": [
    "Documentable:ver<1.2.5+>"
  ],
  "description": "A tool for reading Raku documentation",
  "license": "Artistic-2.0",
  "name": "Rakudoc",
  "perl": "6.d",
  "provides": {
    "Pod::Cache": "lib/Pod/Cache.rakumod",
    "Rakudoc": "lib/Rakudoc.rakumod",
    "Rakudoc::CMD": "lib/Rakudoc/CMD.rakumod"
  },
  "raku": "6.d",
  "resources": [
  ],
  "source-url": "https://github.com/Raku/rakudoc.git",
  "support": {
    "bugtracker": "https://github.com/Raku/rakudoc/issues"
  },
  "tags": [
  ],
  "test-depends": [
    "IO::MiddleMan:ver<1.001003+>",
    "File::Temp:ver<0.0.8+>"
  ],
  "version": "0.1.9"
}
